nameko_cli/__init__.py
nameko_cli/__main__.py
nameko_cli/run.py
nameko_cli/utils.py
nameko_cli/commands/__init__.py
nameko_cli/commands/deploy.py
nameko_cli/commands/project.py
nameko_cli/templates/.gitignore
nameko_cli/templates/Dockerfile
nameko_cli/templates/README.md
nameko_cli/templates/requirements.txt
nameko_cli/templates/config/dev.yml
nameko_cli/templates/config/prod.yml
nameko_cli/templates/service/config.py
nameko_cli/templates/service/models.py
nameko_cli/templates/service/roles.py
nameko_cli/templates/service/service.py
nameko_cli-0.0.6.dist-info/LICENSE
nameko_cli-0.0.6.dist-info/METADATA
nameko_cli-0.0.6.dist-info/WHEEL
nameko_cli-0.0.6.dist-info/entry_points.txt
nameko_cli-0.0.6.dist-info/top_level.txt
nameko_cli-0.0.6.dist-info/RECORD
