Metadata-Version: 2.1
Name: nameko-cli
Version: 0.0.6
Summary: nameko cli tools
Home-page: UNKNOWN
Author: li1234yun
Author-email: li1234yun@163.com
License: UNKNOWN
Platform: UNKNOWN
Classifier: Programming Language :: Python :: 3
Classifier: License :: OSI Approved :: MIT License
Classifier: Operating System :: OS Independent
Requires-Dist: click
